{
    "id": 8,
    "slug": "lesson-8",
    "name": "Review",
    "components": [
        {
            "type": "video",
            "youtubeUrl": "https://youtu.be/JGMuvftBNew?si=H_rBK4pWnSjRs-uC",
            "title": "Review of the Course",
            "description": ""
        },
        {
            "type": "quiz",
            "questions": [
                {
                    "question": "What case is servum in?",
                    "answers": [
                        {
                            "string": "Accusative",
                            "correct": true
                        },
                        {
                            "string": "Nominative",
                            "correct": false
                        },
                        {
                            "string": "Dative",
                            "correct": false
                        },
                        {
                            "string": "Ablative",
                            "correct": false
                        }
                    ]
                },
                {
                    "question": "Translate this sentence: Nos filium vidimus.",
                    "answers": [
                        {
                            "string": "They had seen the brother.",
                            "correct": false
                        },
                        {
                            "string": "We spoke to the son.",
                            "correct": false
                        },
                        {
                            "string": "We see the son.",
                            "correct": true
                        },
                        {
                            "string": "The boy spoke to me.",
                            "correct": false
                        }
                    ]
                },
                {
                    "question": "The number 13 in Roman numerals",
                    "answers": [
                        {
                            "string": "XXXVI",
                            "correct": false
                        },
                        {
                            "string": "XIII",
                            "correct": true
                        },
                        {
                            "string": "CIV",
                            "correct": false
                        },
                        {
                            "string": "DVI",
                            "correct": false
                        }
                    ]
                },
                {
                    "question": "What city was destroyed by Mt. Vesuvius?",
                    "answers": [
                        {
                            "string": "Sicily",
                            "correct": false
                        },
                        {
                            "string": "Pompeii",
                            "correct": true
                        },
                        {
                            "string": "Salernum",
                            "correct": false
                        },
                        {
                            "string": "Belum",
                            "correct": false
                        }
                    ]
                },
                {
                    "question": "What does quartus translate to?",
                    "answers": [
                        {
                            "string": "land",
                            "correct": false
                        },
                        {
                            "string": "fourth",
                            "correct": true
                        },
                        {
                            "string": "fourty",
                            "correct": false
                        },
                        {
                            "string": "quarters",
                            "correct": false
                        }
                    ]
                },
                {
                    "question": "What does the verb salutavit mean?",
                    "answers": [
                        {
                            "string": "greets",
                            "correct": false
                        },
                        {
                            "string": "He, she, it greeted",
                            "correct": true
                        },
                        {
                            "string": "They salute",
                            "correct": false
                        },
                        {
                            "string": "I will be greeted",
                            "correct": false
                        }
                    ]
                },
                {
                    "question": "What is the tense of visitabat?",
                    "answers": [
                        {
                            "string": "Present",
                            "correct": false
                        },
                        {
                            "string": "Perfect",
                            "correct": false
                        },
                        {
                            "string": "Pluperfect",
                            "correct": false
                        },
                        {
                            "string": "Imperfect",
                            "correct": true
                        }
                    ]
                },
                {
                    "question": "Fillius bono",
                    "answers": [
                        {
                            "string": "The smart brother",
                            "correct": false
                        },
                        {
                            "string": "The good son",
                            "correct": true
                        },
                        {
                            "string": "The son is gone",
                            "correct": false
                        },
                        {
                            "string": "A brother is getting better",
                            "correct": false
                        }
                    ]
                },
                {
                    "question": "What is the accusative of a sentence",
                    "answers": [
                        {
                            "string": "Subject",
                            "correct": false
                        },
                        {
                            "string": "Direct object",
                            "correct": true
                        },
                        {
                            "string": "Indirect object",
                            "correct": false
                        },
                        {
                            "string": "Prepositional phrase",
                            "correct": false
                        }
                    ]
                },
                {
                    "question": "What declension and number is magistras",
                    "answers": [
                        {
                            "string": "3rd singular",
                            "correct": false
                        },
                        {
                            "string": "1st plural",
                            "correct": true
                        },
                        {
                            "string": "2nd singular",
                            "correct": false
                        },
                        {
                            "string": "3rd plural",
                            "correct": false
                        }
                    ]
                },
                {
                    "question": "How do adjectives NOT have to agree",
                    "answers": [
                        {
                            "string": "Number",
                            "correct": false
                        },
                        {
                            "string": "Declension",
                            "correct": true
                        },
                        {
                            "string": "Case",
                            "correct": false
                        }
                    ]
                },
                {
                    "question": "What is this Roman numeral: CXVII",
                    "answers": [
                        {
                            "string": "2053",
                            "correct": false
                        },
                        {
                            "string": "59",
                            "correct": false
                        },
                        {
                            "string": "117",
                            "correct": true
                        },
                        {
                            "string": "94",
                            "correct": false
                        }
                    ]
                },
                {
                    "question": "What is the accusative of this sentence: Metella cibum gustat.",
                    "answers": [
                        {
                            "string": "Metella",
                            "correct": false
                        },
                        {
                            "string": "Cibum",
                            "correct": true
                        },
                        {
                            "string": "Gustat",
                            "correct": false
                        },
                        {
                            "string": "Not applicable",
                            "correct": false
                        }
                    ]
                },
                {
                    "question": "What is the dative of this sentence: Grumio est anxius.",
                    "answers": [
                        {
                            "string": "Est",
                            "correct": false
                        },
                        {
                            "string": "Grumio",
                            "correct": false
                        },
                        {
                            "string": "anxius",
                            "correct": false
                        },
                        {
                            "string": "Not applicable",
                            "correct": true
                        }
                    ]
                },
                {
                    "question": "Where did the majority of business and life take place in a Roman city?",
                    "answers": [
                        {
                            "string": "The baths",
                            "correct": false
                        },
                        {
                            "string": "The port",
                            "correct": false
                        },
                        {
                            "string": "The gladiator arena",
                            "correct": false
                        },
                        {
                            "string": "The forum",
                            "correct": true
                        }
                    ]
                },
                {
                    "question": "The Roman religion has one god",
                    "answers": [
                        {
                            "string": "True",
                            "correct": false
                        },
                        {
                            "string": "False",
                            "correct": true
                        }
                    ]
                },
                {
                    "question": "Translate vituperabamus",
                    "answers": [
                        {
                            "string": "They curse out",
                            "correct": false
                        },
                        {
                            "string": "He was cursing out",
                            "correct": false
                        },
                        {
                            "string": "We were cursing out",
                            "correct": true
                        },
                        {
                            "string": "I cursed out.",
                            "correct": false
                        }
                    ]
                },
                {
                    "question": "Meaning of circum-",
                    "answers": [
                        {
                            "string": "Down",
                            "correct": false
                        },
                        {
                            "string": "Around",
                            "correct": true
                        },
                        {
                            "string": "From",
                            "correct": false
                        },
                        {
                            "string": "Towards",
                            "correct": false
                        }
                    ]
                },
                {
                    "question": "What does the nominative case represent in a sentence?",
                    "answers": [
                        {
                            "string": "The prepositional phrase",
                            "correct": false
                        },
                        {
                            "string": "The verb",
                            "correct": false
                        },
                        {
                            "string": "Gerund",
                            "correct": false
                        },
                        {
                            "string": "Subject",
                            "correct": true
                        }
                    ]
                },
                {
                    "question": "The verb trahere means to drag. What does the word extrahere mean?",
                    "answers": [
                        {
                            "string": "To drag towards",
                            "correct": false
                        },
                        {
                            "string": "To drag out",
                            "correct": true
                        },
                        {
                            "string": "To drag down",
                            "correct": false
                        },
                        {
                            "string": "To drag below",
                            "correct": false
                        }
                    ]
                },
                {
                    "question": "What is a triclinium?",
                    "answers": [
                        {
                            "string": "Three column hallway",
                            "correct": false
                        },
                        {
                            "string": "Kitchen",
                            "correct": false
                        },
                        {
                            "string": "Dining room with three couches",
                            "correct": true
                        },
                        {
                            "string": "doorway",
                            "correct": false
                        }
                    ]
                },
                {
                    "question": "Most Romans had slaves.",
                    "answers": [
                        {
                            "string": "True",
                            "correct": false
                        },
                        {
                            "string": "False",
                            "correct": true
                        }
                    ]
                },
                {
                    "question": "The Roman Empire stretched from Western Europe, North Africa, and the parts of the Middle East.",
                    "answers": [
                        {
                            "string": "True",
                            "correct": true
                        },
                        {
                            "string": "False",
                            "correct": false
                        }
                    ]
                },
                {
                    "question": "Translate: mercātor vīllam videt. Filia est in ātriō.",
                    "answers": [
                        {
                            "string": "A robber is in the house. Metella is in the kitchen.",
                            "correct": false
                        },
                        {
                            "string": "The merchant entered the bath. Metella is in the garden.",
                            "correct": false
                        },
                        {
                            "string": "The house is full of guests. Metella is in the garden inside the house.",
                            "correct": false
                        },
                        {
                            "string": "The merchant sees the house. The daughter is in the atrium.",
                            "correct": true
                        }
                    ]
                },
                {
                    "question": "\"Salve!\" Caecilius mercātōrem salūtat. How many people is Caecilus (*a person's name) greeting?",
                    "answers": [
                        {
                            "string": "One",
                            "correct": true
                        },
                        {
                            "string": "None",
                            "correct": false
                        },
                        {
                            "string": "More than one",
                            "correct": false
                        },
                        {
                            "string": "Caecilius is being greeted",
                            "correct": false
                        }
                    ]
                }
            ]
        }
    ]
}